tsignal/__init__.py
tsignal/core.py
tsignal/utils.py
tsignal/contrib/extensions/__init__.py
tsignal/contrib/extensions/property.py
tsignal/contrib/patterns/__init__.py
tsignal/contrib/patterns/worker/__init__.py
tsignal/contrib/patterns/worker/decorators.py
tsignal-0.4.4.dist-info/METADATA
tsignal-0.4.4.dist-info/WHEEL
tsignal-0.4.4.dist-info/top_level.txt
tsignal-0.4.4.dist-info/RECORD
