Metadata-Version: 2.1
Name: tsignal
Version: 0.4.4
Summary: A Python Signal-Slot library inspired by Qt
Author-email: San Kim <tsignal.dev@gmail.com>
License: MIT
Project-URL: Homepage, https://github.com/TSignalDev/tsignal-python
Project-URL: Repository, https://github.com/TSignalDev/tsignal-python
Project-URL: Documentation, https://github.com/TSignalDev/tsignal-python#readme
Project-URL: Issues, https://github.com/TSignalDev/tsignal-python/issues
Keywords: signal-slot,decorator,multithreading,asyncio
Classifier: Development Status :: 3 - Alpha
Classifier: Intended Audience :: Developers
Classifier: License :: OSI Approved :: MIT License
Classifier: Programming Language :: Python :: 3
Classifier: Programming Language :: Python :: 3.10
Classifier: Programming Language :: Python :: 3.11
Classifier: Programming Language :: Python :: 3.12
Classifier: Topic :: Software Development :: Libraries
Requires-Python: >=3.10
Provides-Extra: dev
Requires-Dist: pytest>=7.0; extra == "dev"
Requires-Dist: pytest-cov>=4.0; extra == "dev"
Requires-Dist: pytest-asyncio>=0.21.0; extra == "dev"
Requires-Dist: memory_profiler; extra == "dev"
